MANIFEST.in
README
man-osc-receive.txt
man-osc-send.txt
osc-receive.1
osc-send.1
setup.py
scripts/osc-receive
scripts/osc-send
txosc/__init__.py
txosc/async.py
txosc/dispatch.py
txosc/osc.py
txosc/sync.py
txosc.egg-info/PKG-INFO
txosc.egg-info/SOURCES.txt
txosc.egg-info/dependency_links.txt
txosc.egg-info/top_level.txt
txosc/test/__init__.py
txosc/test/test_async.py
txosc/test/test_dispatch.py
txosc/test/test_osc.py