Metadata-Version: 1.0
Name: txosc
Version: 0.2.0
Summary: Open Sound Control Protocol for Twisted
Home-page: http://bitbucket.org/arjan/txosc
Author: Arjan Scherpenisse and Alexandre Quessy
Author-email: txosc@toonloop.com
License: MIT/X
Platform: UNKNOWN
Classifier: Framework :: Twisted
Classifier: Intended Audience :: Developers
Classifier: License :: OSI Approved :: MIT License
Classifier: Programming Language :: Python
Classifier: Topic :: Communications
Classifier: Topic :: Software Development :: Libraries :: Python Modules
Classifier: Topic :: Utilities
